is_it_slop_preprocessing-0.4.0.dist-info/METADATA
is_it_slop_preprocessing-0.4.0.dist-info/WHEEL
is_it_slop_preprocessing/__init__.py
is_it_slop_preprocessing/_internal.py
is_it_slop_preprocessing/_is_it_slop_preprocessing_rust_bindings.cp312-win_amd64.pyd
is_it_slop_preprocessing/py.typed
is_it_slop_preprocessing-0.4.0.dist-info/RECORD
