Metadata-Version: 2.4
Name: is-it-slop-preprocessing
Version: 0.4.0
Requires-Dist: numpy>=2.0
Requires-Dist: scipy>=1.14
Summary: Fast TF-IDF vectorization with Rust-backed preprocessing
Author-email: SamBroomy <36888606+SamBroomy@users.noreply.github.com>
Requires-Python: >=3.11
